pools_dashboard/__init__.py
pools_dashboard/charts.py
pools_dashboard/dashboard.py
pools_dashboard/etl.py
pools_dashboard-0.1.1.dist-info/WHEEL
pools_dashboard-0.1.1.dist-info/METADATA
pools_dashboard-0.1.1.dist-info/RECORD
